nobeartype/__init__.py
nobeartype/py.typed
nobeartype-0.1.1.dist-info/METADATA
nobeartype-0.1.1.dist-info/WHEEL
nobeartype-0.1.1.dist-info/RECORD
