Metadata-Version: 2.4
Name: nobeartype
Version: 0.1.1
Summary: Bear proof your functions. It's basic stuff.
Author-email: Alexander Socarras <apsocarras@gmail.com>
Requires-Python: >=3.9
Requires-Dist: beartype>=0.21.0
Requires-Dist: typing-extensions>=4.15.0
